Metadata-Version: 2.1
Name: marcumq
Version: 0.0.1
Summary: Marcum Q-function
Home-page: https://github.com/dgerosa/marcumq
Author: Davide Gerosa
Author-email: davide.gerosa@unimib.it
License: MIT
License-File: LICENSE
